setup.py
src/simple_timer/__init__.py
src/simple_timer/tests.py
src/simple_timer.egg-info/PKG-INFO
src/simple_timer.egg-info/SOURCES.txt
src/simple_timer.egg-info/dependency_links.txt
src/simple_timer.egg-info/top_level.txt