Metadata-Version: 1.1
Name: simple-timer
Version: 0.2
Summary: A timer module. Makes it easy to track elapsed time.
Home-page: https://bitbucket.org/barseghyanartur/timer
Author: Artur Barseghyan
Author-email: artur.barseghyan@gmail.com
License: GPL 2.0/LGPL 2.1
Keywords: timer
Platform: UNKNOWN
Classifier: Programming Language :: Python
Classifier: Programming Language :: Python :: 2.6
Classifier: Programming Language :: Python :: 2.7
Classifier: Programming Language :: Python :: 3
Classifier: Programming Language :: Python :: 3.3
Classifier: Intended Audience :: Developers
Classifier: Operating System :: OS Independent
